<?xml version="1.0" encoding="utf-8"?>
<xliff xmlns="urn:oasis:names:tc:xliff:document:1.2" xmlns:xsi="http://www.w3.org/2001/XMLSchema-instance" version="1.2" xsi:schemaLocation="urn:oasis:names:tc:xliff:document:1.2 xliff-core-1.2-transitional.xsd">
  <file datatype="xml" original="ISharePointProjectItemCollection.xml" source-language="en-US" target-language="zh-CN">
    <header>
      <tool tool-id="mdxliff" tool-name="mdxliff" tool-version="1.0-38f25dd" tool-company="Microsoft" />
      <xliffext:skl_file_name xmlns:xliffext="urn:microsoft:content:schema:xliffextensions">b4690f9a-9e49-426d-9091-855b10fda4dbd901f7a862dd8d49dec9612ff20583737e6c5480.skl</xliffext:skl_file_name>
      <xliffext:version xmlns:xliffext="urn:microsoft:content:schema:xliffextensions">1.2</xliffext:version>
      <xliffext:ms.openlocfilehash xmlns:xliffext="urn:microsoft:content:schema:xliffextensions">d901f7a862dd8d49dec9612ff20583737e6c5480</xliffext:ms.openlocfilehash>
      <xliffext:ms.sourcegitcommit xmlns:xliffext="urn:microsoft:content:schema:xliffextensions">bb8a3a96823cedeffbdbcc0c41a8118399de8074</xliffext:ms.sourcegitcommit>
      <xliffext:ms.lasthandoff xmlns:xliffext="urn:microsoft:content:schema:xliffextensions">02/21/2018</xliffext:ms.lasthandoff>
      <xliffext:moniker_ids xmlns:xliffext="urn:microsoft:content:schema:xliffextensions">sharepoint-projects-2017</xliffext:moniker_ids>
    </header>
    <body>
      <group id="content" extype="content">
        <trans-unit id="101" translate="yes" xml:space="preserve" uid="T:Microsoft.VisualStudio.SharePoint.ISharePointProjectItemCollection">
          <source>Represents a collection of SharePoint project items.</source>
          <target state="translated">表示 SharePoint 项目项的集合。</target>       </trans-unit>
        <trans-unit id="102" translate="yes" xml:space="preserve" uid="M:Microsoft.VisualStudio.SharePoint.ISharePointProjectItemCollection.Add(System.String,System.String)">
          <source>The name of SharePoint project item to add.</source>
          <target state="translated">要添加的 SharePoint 项目项的名称。</target>       </trans-unit>
        <trans-unit id="103" translate="yes" xml:space="preserve" uid="M:Microsoft.VisualStudio.SharePoint.ISharePointProjectItemCollection.Add(System.String,System.String)">
          <source>The type ID of the SharePoint project item to add.</source>
          <target state="translated">要添加的 SharePoint 项目项的类型 ID。</target>       </trans-unit>
        <trans-unit id="104" translate="yes" xml:space="preserve" uid="M:Microsoft.VisualStudio.SharePoint.ISharePointProjectItemCollection.Add(System.String,System.String)">
          <source>Creates and adds a new instance of a SharePoint project item.</source>
          <target state="translated">创建并添加 SharePoint 项目项的新实例。</target>       </trans-unit>
        <trans-unit id="105" translate="yes" xml:space="preserve" uid="M:Microsoft.VisualStudio.SharePoint.ISharePointProjectItemCollection.Add(System.String,System.String)">
          <source>An instance of the SharePoint project item that was added.</source>
          <target state="translated">已添加的 SharePoint 项目项的实例。</target>       </trans-unit>
        <trans-unit id="106" translate="yes" xml:space="preserve" uid="M:Microsoft.VisualStudio.SharePoint.ISharePointProjectItemCollection.Add(System.String,System.String)">
          <source>Occurs if any of the arguments are <ph id="ph1">&lt;see langword="null" /&gt;</ph>.</source>
          <target state="translated">当任一参数为 <ph id="ph1">&lt;see langword="null" /&gt;</ph> 时发生。</target>       </trans-unit>
        <trans-unit id="107" translate="yes" xml:space="preserve" uid="M:Microsoft.VisualStudio.SharePoint.ISharePointProjectItemCollection.Add(System.String,System.String)">
          <source>Occurs in the following cases:</source>
          <target state="translated">在以下情况下发生：</target>       </trans-unit>
        <trans-unit id="108" translate="yes" xml:space="preserve" uid="M:Microsoft.VisualStudio.SharePoint.ISharePointProjectItemCollection.Add(System.String,System.String)">
          <source>If any of the parameters are empty strings.</source>
          <target state="translated">如果任一参数为空字符串。</target>       </trans-unit>
        <trans-unit id="109" translate="yes" xml:space="preserve" uid="M:Microsoft.VisualStudio.SharePoint.ISharePointProjectItemCollection.Add(System.String,System.String)">
          <source>If a SharePoint project item with the provided name already exists.</source>
          <target state="translated">如果已存在具有所提供名称的 SharePoint 项目项。</target>       </trans-unit>
        <trans-unit id="110" translate="yes" xml:space="preserve" uid="M:Microsoft.VisualStudio.SharePoint.ISharePointProjectItemCollection.Add(System.String,System.String,System.Boolean)">
          <source>The name of a SharePoint project item to add.</source>
          <target state="translated">要添加的 SharePoint 项目项的名称。</target>       </trans-unit>
        <trans-unit id="111" translate="yes" xml:space="preserve" uid="M:Microsoft.VisualStudio.SharePoint.ISharePointProjectItemCollection.Add(System.String,System.String,System.Boolean)">
          <source>The type ID of the SharePoint project item to add.</source>
          <target state="translated">要添加的 SharePoint 项目项的类型 ID。</target>       </trans-unit>
        <trans-unit id="112" translate="yes" xml:space="preserve" uid="M:Microsoft.VisualStudio.SharePoint.ISharePointProjectItemCollection.Add(System.String,System.String,System.Boolean)">
          <source>Skips auto-add to a first available feature if <ph id="ph1">&lt;see langword="true" /&gt;</ph>.</source>
          <target state="translated">如果为 <ph id="ph1">&lt;see langword="true" /&gt;</ph>，则跳过自动添加，转到第一个可用功能。</target>       </trans-unit>
        <trans-unit id="113" translate="yes" xml:space="preserve" uid="M:Microsoft.VisualStudio.SharePoint.ISharePointProjectItemCollection.Add(System.String,System.String,System.Boolean)">
          <source>Creates and adds a new instance of SharePoint project item.</source>
          <target state="translated">创建并添加 SharePoint 项目项的新实例。</target>       </trans-unit>
        <trans-unit id="114" translate="yes" xml:space="preserve" uid="M:Microsoft.VisualStudio.SharePoint.ISharePointProjectItemCollection.Add(System.String,System.String,System.Boolean)">
          <source>An instance of the SharePoint project item that was added.</source>
          <target state="translated">已添加的 SharePoint 项目项的实例。</target>       </trans-unit>
        <trans-unit id="115" translate="yes" xml:space="preserve" uid="M:Microsoft.VisualStudio.SharePoint.ISharePointProjectItemCollection.Add(System.String,System.String,System.Boolean)">
          <source>Occurs if any of the arguments are <ph id="ph1">&lt;see langword="null" /&gt;</ph>.</source>
          <target state="translated">当任一参数为 <ph id="ph1">&lt;see langword="null" /&gt;</ph> 时发生。</target>       </trans-unit>
        <trans-unit id="116" translate="yes" xml:space="preserve" uid="M:Microsoft.VisualStudio.SharePoint.ISharePointProjectItemCollection.Add(System.String,System.String,System.Boolean)">
          <source>Occurs in the following cases:</source>
          <target state="translated">在以下情况下发生：</target>       </trans-unit>
        <trans-unit id="117" translate="yes" xml:space="preserve" uid="M:Microsoft.VisualStudio.SharePoint.ISharePointProjectItemCollection.Add(System.String,System.String,System.Boolean)">
          <source>If any of the parameters are empty strings.</source>
          <target state="translated">如果任一参数为空字符串。</target>       </trans-unit>
        <trans-unit id="118" translate="yes" xml:space="preserve" uid="M:Microsoft.VisualStudio.SharePoint.ISharePointProjectItemCollection.Add(System.String,System.String,System.Boolean)">
          <source>If a SharePoint project item with the provided name already exists.</source>
          <target state="translated">如果已存在具有所提供名称的 SharePoint 项目项。</target>       </trans-unit>
        <trans-unit id="119" translate="yes" xml:space="preserve" uid="M:Microsoft.VisualStudio.SharePoint.ISharePointProjectItemCollection.Add(System.String,System.String,System.String)">
          <source>The subfolder in the project where the new SharePoint item is created.</source>
          <target state="translated">项目中创建新的 SharePoint 项的子文件夹。</target>       </trans-unit>
        <trans-unit id="120" translate="yes" xml:space="preserve" uid="M:Microsoft.VisualStudio.SharePoint.ISharePointProjectItemCollection.Add(System.String,System.String,System.String)">
          <source>The name of SharePoint project item to be added.</source>
          <target state="translated">要添加的 SharePoint 项目项的名称。</target>       </trans-unit>
        <trans-unit id="121" translate="yes" xml:space="preserve" uid="M:Microsoft.VisualStudio.SharePoint.ISharePointProjectItemCollection.Add(System.String,System.String,System.String)">
          <source>The type ID of the SharePoint project item to be added.</source>
          <target state="translated">要添加的 SharePoint 项目项的类型 ID。</target>       </trans-unit>
        <trans-unit id="122" translate="yes" xml:space="preserve" uid="M:Microsoft.VisualStudio.SharePoint.ISharePointProjectItemCollection.Add(System.String,System.String,System.String)">
          <source>Creates and adds a new instance of SharePoint project item.</source>
          <target state="translated">创建并添加 SharePoint 项目项的新实例。</target>       </trans-unit>
        <trans-unit id="123" translate="yes" xml:space="preserve" uid="M:Microsoft.VisualStudio.SharePoint.ISharePointProjectItemCollection.Add(System.String,System.String,System.String)">
          <source>An instance of the SharePoint project item that was added.</source>
          <target state="translated">已添加的 SharePoint 项目项的实例。</target>       </trans-unit>
        <trans-unit id="124" translate="yes" xml:space="preserve" uid="M:Microsoft.VisualStudio.SharePoint.ISharePointProjectItemCollection.Add(System.String,System.String,System.String)">
          <source>Occurs if any of the arguments are <ph id="ph1">&lt;see langword="null" /&gt;</ph>.</source>
          <target state="translated">当任一参数为 <ph id="ph1">&lt;see langword="null" /&gt;</ph> 时发生。</target>       </trans-unit>
        <trans-unit id="125" translate="yes" xml:space="preserve" uid="M:Microsoft.VisualStudio.SharePoint.ISharePointProjectItemCollection.Add(System.String,System.String,System.String)">
          <source>Occurs in the following cases:</source>
          <target state="translated">在以下情况下发生：</target>       </trans-unit>
        <trans-unit id="126" translate="yes" xml:space="preserve" uid="M:Microsoft.VisualStudio.SharePoint.ISharePointProjectItemCollection.Add(System.String,System.String,System.String)">
          <source>If any of the parameters are empty strings.</source>
          <target state="translated">如果任一参数为空字符串。</target>       </trans-unit>
        <trans-unit id="127" translate="yes" xml:space="preserve" uid="M:Microsoft.VisualStudio.SharePoint.ISharePointProjectItemCollection.Add(System.String,System.String,System.String)">
          <source>If the path is not a valid absolute path (that is, not under the project root path).</source>
          <target state="translated">如果路径不是有效的绝对路径（即不在项目根路径下）。</target>       </trans-unit>
        <trans-unit id="128" translate="yes" xml:space="preserve" uid="M:Microsoft.VisualStudio.SharePoint.ISharePointProjectItemCollection.Add(System.String,System.String,System.String)">
          <source>If a SharePoint project item with the provided name already exists.</source>
          <target state="translated">如果已存在具有所提供名称的 SharePoint 项目项。</target>       </trans-unit>
        <trans-unit id="129" translate="yes" xml:space="preserve" uid="M:Microsoft.VisualStudio.SharePoint.ISharePointProjectItemCollection.Add(System.String,System.String,System.String,System.Boolean)">
          <source>The base path of the project item.</source>
          <target state="translated">项目项的基路径。</target>       </trans-unit>
        <trans-unit id="130" translate="yes" xml:space="preserve" uid="M:Microsoft.VisualStudio.SharePoint.ISharePointProjectItemCollection.Add(System.String,System.String,System.String,System.Boolean)">
          <source>Can be either relative to the project path or absolute.</source>
          <target state="translated">可以是相对项目路径，也可以是绝对项目路径。</target>       </trans-unit>
        <trans-unit id="131" translate="yes" xml:space="preserve" uid="M:Microsoft.VisualStudio.SharePoint.ISharePointProjectItemCollection.Add(System.String,System.String,System.String,System.Boolean)">
          <source>The name of the project item.</source>
          <target state="translated">项目项的名称。</target>       </trans-unit>
        <trans-unit id="132" translate="yes" xml:space="preserve" uid="M:Microsoft.VisualStudio.SharePoint.ISharePointProjectItemCollection.Add(System.String,System.String,System.String,System.Boolean)">
          <source>The name should be file system-friendly.</source>
          <target state="translated">名称应该为文件系统友好型。</target>       </trans-unit>
        <trans-unit id="133" translate="yes" xml:space="preserve" uid="M:Microsoft.VisualStudio.SharePoint.ISharePointProjectItemCollection.Add(System.String,System.String,System.String,System.Boolean)">
          <source>The type of the project item.</source>
          <target state="translated">项目项的类型。</target>       </trans-unit>
        <trans-unit id="134" translate="yes" xml:space="preserve" uid="M:Microsoft.VisualStudio.SharePoint.ISharePointProjectItemCollection.Add(System.String,System.String,System.String,System.Boolean)">
          <source>If <ph id="ph1">&lt;see langword="true" /&gt;</ph>, the project system will not automatically add a feature or package for the project item.</source>
          <target state="translated">如果为 <ph id="ph1">&lt;see langword="true" /&gt;</ph>，项目系统不会自动添加项目项的功能或包。</target>       </trans-unit>
        <trans-unit id="135" translate="yes" xml:space="preserve" uid="M:Microsoft.VisualStudio.SharePoint.ISharePointProjectItemCollection.Add(System.String,System.String,System.String,System.Boolean)">
          <source>Creates and adds a SharePoint project item to the project.</source>
          <target state="translated">创建 SharePoint 项目项，并将其添加到项目。</target>       </trans-unit>
        <trans-unit id="136" translate="yes" xml:space="preserve" uid="M:Microsoft.VisualStudio.SharePoint.ISharePointProjectItemCollection.Add(System.String,System.String,System.String,System.Boolean)">
          <source>An instance of the new project item.</source>
          <target state="translated">新项目项的实例。</target>       </trans-unit>
        <trans-unit id="137" translate="yes" xml:space="preserve" uid="M:Microsoft.VisualStudio.SharePoint.ISharePointProjectItemCollection.Add(System.String,System.String,System.String,System.Boolean)">
          <source>Occurs if any of the arguments are <ph id="ph1">&lt;see langword="null" /&gt;</ph>.</source>
          <target state="translated">当任一参数为 <ph id="ph1">&lt;see langword="null" /&gt;</ph> 时发生。</target>       </trans-unit>
        <trans-unit id="138" translate="yes" xml:space="preserve" uid="M:Microsoft.VisualStudio.SharePoint.ISharePointProjectItemCollection.Add(System.String,System.String,System.String,System.Boolean)">
          <source>Occurs in the following cases:</source>
          <target state="translated">在以下情况下发生：</target>       </trans-unit>
        <trans-unit id="139" translate="yes" xml:space="preserve" uid="M:Microsoft.VisualStudio.SharePoint.ISharePointProjectItemCollection.Add(System.String,System.String,System.String,System.Boolean)">
          <source>If any of the parameters are empty strings.</source>
          <target state="translated">如果任一参数为空字符串。</target>       </trans-unit>
        <trans-unit id="140" translate="yes" xml:space="preserve" uid="M:Microsoft.VisualStudio.SharePoint.ISharePointProjectItemCollection.Add(System.String,System.String,System.String,System.Boolean)">
          <source>If the path is not a valid absolute path (that is, not under the project root path).</source>
          <target state="translated">如果路径不是有效的绝对路径（即不在项目根路径下）。</target>       </trans-unit>
        <trans-unit id="141" translate="yes" xml:space="preserve" uid="M:Microsoft.VisualStudio.SharePoint.ISharePointProjectItemCollection.Add(System.String,System.String,System.String,System.Boolean)">
          <source>If a SharePoint project item with the provided name already exists.</source>
          <target state="translated">如果已存在具有所提供名称的 SharePoint 项目项。</target>       </trans-unit>
        <trans-unit id="142" translate="yes" xml:space="preserve" uid="M:Microsoft.VisualStudio.SharePoint.ISharePointProjectItemCollection.Find(System.Guid)">
          <source>The ID of the SharePoint project item instance to find.</source>
          <target state="translated">要查找的 SharePoint 项目项实例的 ID。</target>       </trans-unit>
        <trans-unit id="143" translate="yes" xml:space="preserve" uid="M:Microsoft.VisualStudio.SharePoint.ISharePointProjectItemCollection.Find(System.Guid)">
          <source>Finds a <ph id="ph1">&lt;see cref="T:Microsoft.VisualStudio.SharePoint.ISharePointProjectItem" /&gt;</ph> instance by its ID.</source>
          <target state="translated">按其 ID 查找 <ph id="ph1">&lt;see cref="T:Microsoft.VisualStudio.SharePoint.ISharePointProjectItem" /&gt;</ph> 实例。</target>       </trans-unit>
        <trans-unit id="144" translate="yes" xml:space="preserve" uid="M:Microsoft.VisualStudio.SharePoint.ISharePointProjectItemCollection.Find(System.Guid)">
          <source>An object representing the SharePoint project item instance if it found; <ph id="ph1">&lt;see langword="null" /&gt;</ph> otherwise.</source>
          <target state="translated">如果找到，则为表示 SharePoint 项目项实例的对象；否则为 <ph id="ph1">&lt;see langword="null" /&gt;</ph>。</target>       </trans-unit>
        <trans-unit id="145" translate="yes" xml:space="preserve" uid="P:Microsoft.VisualStudio.SharePoint.ISharePointProjectItemCollection.Item(System.String)">
          <source>A <ph id="ph1">&lt;see cref="T:Microsoft.VisualStudio.SharePoint.ISharePointProjectItem" /&gt;</ph> folder path.</source>
          <target state="translated"><ph id="ph1">&lt;see cref="T:Microsoft.VisualStudio.SharePoint.ISharePointProjectItem" /&gt;</ph> 文件夹路径。</target>       </trans-unit>
        <trans-unit id="146" translate="yes" xml:space="preserve" uid="P:Microsoft.VisualStudio.SharePoint.ISharePointProjectItemCollection.Item(System.String)">
          <source>Gets an instance of a <ph id="ph1">&lt;see cref="T:Microsoft.VisualStudio.SharePoint.ISharePointProjectItem" /&gt;</ph> by its folder path.</source>
          <target state="translated">按其文件夹路径获取 <ph id="ph1">&lt;see cref="T:Microsoft.VisualStudio.SharePoint.ISharePointProjectItem" /&gt;</ph> 的实例。</target>       </trans-unit>
        <trans-unit id="147" translate="yes" xml:space="preserve" extradata="MT" uid="P:Microsoft.VisualStudio.SharePoint.ISharePointProjectItemCollection.Item(System.String)">
          <source>An instance of a SharePoint project item if it is found; <ph id="ph1">&lt;see langword="null" /&gt;</ph> or <ph id="ph2">&lt;see langword="Nothing" /&gt;</ph> otherwise.</source>
          <target state="translated">如果它找到，则 SharePoint 项目项的实例<ph id="ph1">&lt;see langword="null" /&gt;</ph>或<ph id="ph2">&lt;see langword="Nothing" /&gt;</ph>否则为。</target>       </trans-unit>
        <trans-unit id="148" translate="yes" xml:space="preserve" extradata="MT" uid="P:Microsoft.VisualStudio.SharePoint.ISharePointProjectItemCollection.Item(System.String)">
          <source><ph id="ph1">`folderPath`</ph> can be either an absolute folder path or a relative path to the project folder.</source>
          <target state="translated"><ph id="ph1">`folderPath`</ph> 可以是绝对文件夹路径或项目文件夹的相对路径。</target>       </trans-unit>
        <trans-unit id="149" translate="yes" xml:space="preserve" uid="P:Microsoft.VisualStudio.SharePoint.ISharePointProjectItemCollection.Project">
          <source>Gets the project instance owning this collection.</source>
          <target state="translated">获取拥有此集合的项目实例。</target>       </trans-unit>
        <trans-unit id="150" translate="yes" xml:space="preserve" extradata="MT" uid="P:Microsoft.VisualStudio.SharePoint.ISharePointProjectItemCollection.Project">
          <source>An object representing a project instance.</source>
          <target state="translated">表示一个项目实例的对象。</target>       </trans-unit>
      </group>
    </body>
  </file>
</xliff>